[
  {
    "id": "3de1ac5e-dcf9-4569-a35c-626776c7e42d",
    "data": [
      {
        "text": "who is priyanka tripathy",
        "userDefined": false
      }
    ],
    "isTemplate": false,
    "count": 0,
    "updated": 1551798160
  },
  {
    "id": "6e473ebc-2525-404f-924f-b84a8646e12f",
    "data": [
      {
        "text": "give me information about priyanka mam",
        "userDefined": false
      }
    ],
    "isTemplate": false,
    "count": 0,
    "updated": 1551798160
  },
  {
    "id": "c023e4c3-ab54-4ed9-8219-3100e073ab03",
    "data": [
      {
        "text": "tell me about Priyanka ma\u0027am",
        "userDefined": false
      }
    ],
    "isTemplate": false,
    "count": 0,
    "updated": 0
  },
  {
    "id": "00be0239-24b8-4159-8fe1-ec3fb62040a8",
    "data": [
      {
        "text": "show me photo of priyankaa mam",
        "userDefined": false
      }
    ],
    "isTemplate": false,
    "count": 0,
    "updated": 1551763373
  },
  {
    "id": "e214da5e-1aa2-4c64-afee-454e8767fcf0",
    "data": [
      {
        "text": "say something about  priyanka tripathy mam",
        "userDefined": false
      }
    ],
    "isTemplate": false,
    "count": 0,
    "updated": 1551763373
  },
  {
    "id": "b6e8bb2e-c275-4057-9d88-25f6a4265e4a",
    "data": [
      {
        "text": "tell me",
        "meta": "@sys.ignore",
        "userDefined": false
      },
      {
        "text": " who is priyanka tripathy",
        "userDefined": false
      }
    ],
    "isTemplate": false,
    "count": 0,
    "updated": 1551763373
  },
  {
    "id": "9d6603a0-305d-4aa8-a932-ca58d9f8dd14",
    "data": [
      {
        "text": "tell me",
        "meta": "@sys.ignore",
        "userDefined": false
      },
      {
        "text": " about priyanka mam",
        "userDefined": false
      }
    ],
    "isTemplate": false,
    "count": 0,
    "updated": 1551763373
  },
  {
    "id": "41fa126f-af90-4a9d-b7fd-2429f68186ec",
    "data": [
      {
        "text": "who is priyanka mam",
        "userDefined": false
      }
    ],
    "isTemplate": false,
    "count": 0,
    "updated": 1551763373
  },
  {
    "id": "20bd1c3e-d266-408d-a7e4-6e0e1eb69435",
    "data": [
      {
        "text": "DR. PRIYANKA TRIPATHY",
        "userDefined": false
      }
    ],
    "isTemplate": false,
    "count": 0,
    "updated": 1551763373
  }
]